Workbook

Sheet 01_Dashboard
A1: UNIT 77 MBR SUPER EXPERT — 01_DASHBOARD
A2: Real-Time Operational Cockpit & Supervisory Overview | Author: Turgunjon Ruziboyev | Physics + AI Decision Support
A4: OVERALL MBR KPI | B4: PLANT TOTAL | C4: TRAIN A | D4: TRAIN B | E4: TRAIN C | F4: TRAIN D | G4: STATUS / TARGET
A5: Train Online Status | B5: 4 / 4 ONLINE | C5: ONLINE | D5: ONLINE | E5: ONLINE | F5: ONLINE | G5: ALL ONLINE
A6: Operating Flux (LMH) | B6: =AVERAGE(C6:F6) | C6: ='04_Train_Analysis'!C7 | D6: ='04_Train_Analysis'!D7 | E6: ='04_Train_Analysis'!E7 | F6: ='04_Train_Analysis'!F7 | G6: Design: 24 LMH
A7: Transmembrane Press. (kPa) | B7: =AVERAGE(C7:F7) | C7: ='04_Train_Analysis'!C8 | D7: ='04_Train_Analysis'!D8 | E7: ='04_Train_Analysis'!E8 | F7: ='04_Train_Analysis'!F8 | G7: < 35 kPa (Crit: 60)
A8: Norm. Permeability @20C | B8: =AVERAGE(C8:F8) | C8: ='04_Train_Analysis'!C9 | D8: ='04_Train_Analysis'!D9 | E8: ='04_Train_Analysis'!E9 | F8: ='04_Train_Analysis'!F9 | G8: > 150 LMH/bar
A9: Fouling Velocity (kPa/h) | B9: =MAX(C9:F9) | C9: ='04_Train_Analysis'!C10 | D9: ='04_Train_Analysis'!D10 | E9: ='04_Train_Analysis'!E10 | F9: ='04_Train_Analysis'!F10 | G9: < 0.5 kPa/h
A10: Air Scour SAD_m (Nm3/m2/h) | B10: =AVERAGE(C10:F10) | C10: ='04_Train_Analysis'!C11 | D10: ='04_Train_Analysis'!D11 | E10: ='04_Train_Analysis'!E11 | F10: ='04_Train_Analysis'!F11 | G10: Design: 0.28
A11: Permeate Flow (m3/h) | B11: =SUM(C11:F11) | C11: ='04_Train_Analysis'!C12 | D11: ='04_Train_Analysis'!D12 | E11: ='04_Train_Analysis'!E12 | F11: ='04_Train_Analysis'!F12 | G11: Design: 460.8 m3/h
A12: Fouling Risk Index (0-100) | B12: =MAX(C12:F12) | C12: ='04_Train_Analysis'!C13 | D12: ='04_Train_Analysis'!D13 | E12: ='04_Train_Analysis'!E13 | F12: ='04_Train_Analysis'!F13 | G12: LOW (< 35)
A13: Permeate Turbidity (NTU) | B13: =MAX(C13:F13) | C13: ='04_Train_Analysis'!C14 | D13: ='04_Train_Analysis'!D14 | E13: ='04_Train_Analysis'!E14 | F13: ='04_Train_Analysis'!F14 | G13: < 0.20 NTU
A14: Days Since Last Clean | B14: =MIN(C14:F14) | C14: ='04_Train_Analysis'!C15 | D14: ='04_Train_Analysis'!D15 | E14: ='04_Train_Analysis'!E15 | F14: ='04_Train_Analysis'!F15 | G14: MC Cycle: 7-14 d
A17: PLANT BIOLOGY & SOLIDS INVENTORY
A18: Bioreactor MLSS (mg/L) | B18: ='07_Biology'!B5 | C18: Calculated SRT (days) | D18: ='08_WAS_SRT'!B9 | E18: Active Alarms Count | F18: ='11_Events_Alarms'!B4 | G18: NORMAL
A19: Membrane MLSS (mg/L) | B19: ='07_Biology'!B6 | C19: Daily WAS Flow (m3/d) | D19: ='08_WAS_SRT'!B6 | E19: Data Quality Rating | F19: ='16_Data_Quality'!B5 | G19: 99.4% GOOD
A20: MLVSS/MLSS Ratio | B20: ='07_Biology'!B8 | C20: Water Temp (°C) | D20: ='02_Manual_Input'!B7 | E20: Analytical Engine Mode | F20: EXCEL CORE (Native) | G20: READY

Sheet 02_Manual_Input
A1: UNIT 77 MBR SUPER EXPERT — 02_MANUAL_INPUT
A2: Operator Entry & Laboratory Measurements (Editable Inputs in Blue Cells) | Author: Turgunjon Ruziboyev | Physics + AI Decision Support
A4: PARAMETER NAME | B4: INPUT VALUE | C4: UNIT | D4: SOURCE / GUIDANCE | E4: LAST UPDATED
A5: Raw Influent Flow Q_in | B5: 650 | C5: m3/h | D5: SCADA FIT-7701 (Total Feed Flow) | E5: 2026-09-18 12:00
A6: Influent Temperature | B6: 18.5 | C6: °C | D6: SCADA TT-7701 | E6: 2026-09-18 12:00
A7: Aeration Tank MLSS (Lab) | B7: 7400 | C7: mg/L | D7: Daily 24h Composite Lab Test | E7: 2026-09-18 08:00
A8: Membrane Tank MLSS (Lab) | B8: 9200 | C8: mg/L | D8: Daily 24h Composite Lab Test | E8: 2026-09-18 08:00
A9: Mixed Liquor MLVSS (Lab) | B9: 6600 | C9: mg/L | D9: Furnace 550°C Ashing Method | E9: 2026-09-18 08:00
A10: Influent COD (Lab) | B10: 420 | C10: mg/L | D10: Daily Composite Lab Spectrophotometry | E10: 2026-09-18 08:00
A11: Permeate COD (Lab) | B11: 18.5 | C11: mg/L | D11: Daily Composite Permeate | E11: 2026-09-18 08:00
A12: Daily WAS Sludge Volume | B12: 38 | C12: m3/d | D12: Daily Totalizer Flow FIT-7750 | E12: 2026-09-18 00:00
A13: Aeration Basin DO Setpoint | B13: 2.2 | C13: mg/L | D13: Process Operator Target | E13: 2026-09-18 06:00
A14: Train A Permeate Suction Pressure | B14: -18.5 | C14: kPa | D14: PT-771A Permeate Header Gauge | E14: 2026-09-18 12:00
A15: Train B Permeate Suction Pressure | B15: -19.2 | C15: kPa | D15: PT-771B Permeate Header Gauge | E15: 2026-09-18 12:00
A16: Train C Permeate Suction Pressure | B16: -21 | C16: kPa | D16: PT-771C Permeate Header Gauge | E16: 2026-09-18 12:00
... A26: Train D Air Scour Flow | B26: 1344 | C26: Nm3/h | D26: FIT-772D Coarse Aeration Grid | E26: 2026-09-18 12:00

Sheet 03_Data_Staging
A1: UNIT 77 MBR SUPER EXPERT — 03_DATA_STAGING
A2: 15-Minute Aggregated Process Feature Store with Data Quality Flags | Author: Turgunjon Ruziboyev | Physics + AI Decision Support
A4: TIMESTAMP | B4: TRAIN ID | C4: PERM FLOW (m3/h) | D4: SUCT PRESS (kPa) | E4: TMP (kPa) | F4: FLUX (LMH) | G4: LP_20 (LMH/bar) | H4: AIR (Nm3/h) | I4: DQ FLAG
A5: 2026-09-18 10:0:00 | B5: TRAIN_A | C5: 115.2 | D5: -19 | E5: =(3.2*9.81)-D5 | F5: =(C5*1000)/4800 | G5: =F5/(E5/100)*1.025^(20-18.5) | H5: 1344 | I5: DQ_GOOD
A6: 2026-09-18 10:15:00 | B6: TRAIN_B | C6: 115.2 | D6: -19.3 | E6: =(3.2*9.81)-D6 | F6: =(C6*1000)/4800 | G6: =F6/(E6/100)*1.025^(20-18.5) | H6: 1344 | I6: DQ_GOOD
A7: 2026-09-18 10:30:00 | B7: TRAIN_C | C7: 115.2 | D7: -19.6 | E7: =(3.2*9.81)-D7 | F7: =(C7*1000)/4800 | G7: =F7/(E7/100)*1.025^(20-18.5) | H7: 1344 | I7: DQ_GOOD
A8: 2026-09-18 10:45:00 | B8: TRAIN_D | C8: 115.2 | D8: -19.9 | E8: =(3.2*9.81)-D8 | F8: =(C8*1000)/4800 | G8: =F8/(E8/100)*1.025^(20-18.5) | H8: 1344 | I8: DQ_GOOD
A9: 2026-09-18 11:0:00 | B9: TRAIN_A | C9: 115.2 | D9: -20.2 | E9: =(3.2*9.81)-D9 | F9: =(C9*1000)/4800 | G9: =F9/(E9/100)*1.025^(20-18.5) | H9: 1344 | I9: DQ_GOOD
A10: 2026-09-18 11:15:00 | B10: TRAIN_B | C10: 115.2 | D10: -20.5 | E10: =(3.2*9.81)-D10 | F10: =(C10*1000)/4800 | G10: =F10/(E10/100)*1.025^(20-18.5) | H10: 1344 | I10: DQ_GOOD
A11: 2026-09-18 11:30:00 | B11: TRAIN_C | C11: 115.2 | D11: -20.8 | E11: =(3.2*9.81)-D11 | F11: =(C11*1000)/4800 | G11: =F11/(E11/100)*1.025^(20-18.5) | H11: 1344 | I11: DQ_GOOD
A12: 2026-09-18 11:45:00 | B12: TRAIN_D | C12: 115.2 | D12: -21.1 | E12: =(3.2*9.81)-D12 | F12: =(C12*1000)/4800 | G12: =F12/(E12/100)*1.025^(20-18.5) | H12: 1344 | I12: DQ_GOOD

Sheet 04_Train_Analysis
A1: UNIT 77 MBR SUPER EXPERT — 04_TRAIN_ANALYSIS
A2: Train-by-Train Comparative Membrane Hydraulics & Fouling KPIs | Author: Turgunjon Ruziboyev | Physics + AI Decision Support
A4: TRAIN PARAMETER | B4: UNIT | C4: TRAIN A | D4: TRAIN B | E4: TRAIN C | F4: TRAIN D | G4: CALCULATION FORMULA
A5: Active Membrane Area | B5: m2 | C5: 4800 | D5: 4800 | E5: 4800 | F5: 4800 | G5: Settings: 4 cass * 24 mod * 50 m2
A6: Permeate Suction Pressure | B6: kPa | C6: ='02_Manual_Input'!B14 | D6: ='02_Manual_Input'!B15 | E6: ='02_Manual_Input'!B16 | F6: ='02_Manual_Input'!B17 | G6: Transmitter PT-771x
A7: Operating Flux J | B7: LMH | C7: =('02_Manual_Input'!B18*1000)/C5 | D7: =('02_Manual_Input'!B19*1000)/D5 | E7: =('02_Manual_Input'!B20*1000)/E5 | F7: =('02_Manual_Input'!B21*1000)/F5 | G7: (Q_p * 1000) / Area
A8: Transmembrane Pressure (TMP) | B8: kPa | C8: =('02_Manual_Input'!B22*9.81)-C6 | D8: =('02_Manual_Input'!B22*9.81)-D6 | E8: =('02_Manual_Input'!B22*9.81)-E6 | F8: =('02_Manual_Input'!B22*9.81)-F6 | G8: rho*g*H_tank - P_suction
A9: Normalized Permeability Lp_20 | B9: LMH/bar | C9: =C7/(C8/100)*1.025^(20-'02_Manual_Input'!B6) | D9: =D7/(D8/100)*1.025^(20-'02_Manual_Input'!B6) | E9: =E7/(E8/100)*1.025^(20-'02_Manual_Input'!B6) | F9: =F7/(F8/100)*1.025^(20-'02_Manual_Input'!B6) | G9: (Flux / (TMP/100)) * TCF
A10: Hourly Fouling Rate dTMP/dt | B10: kPa/h | C10: 0.12 | D10: 0.15 | E10: 0.28 | F10: 0.18 | G10: Regression slope over 4 hours
A11: Specific Air Demand SAD_m | B11: Nm3/m2/h | C11: ='02_Manual_Input'!B23/C5 | D11: ='02_Manual_Input'!B24/D5 | E11: ='02_Manual_Input'!B25/E5 | F11: ='02_Manual_Input'!B26/F5 | G11: Air_Scour_Flow / Membrane_Area
A12: Permeate Flow Rate Q_p | B12: m3/h | C12: ='02_Manual_Input'!B18 | D12: ='02_Manual_Input'!B19 | E12: ='02_Manual_Input'!B20 | F12: ='02_Manual_Input'!B21 | G12: SCADA FIT-771x
A13: Fouling Risk Score (0-100) | B13: pts | C13: =ROUND((C8/60*50)+(C10/1.2*50), 0) | D13: =ROUND((D8/60*50)+(D10/1.2*50), 0) | E13: =ROUND((E8/60*50)+(E10/1.2*50), 0) | F13: =ROUND((F8/60*50)+(F10/1.2*50), 0) | G13: Weighted TMP & dTMP/dt index
A14: Permeate Turbidity | B14: NTU | C14: 0.06 | D14: 0.08 | E14: 0.07 | F14: 0.09 | G14: Optical Turbidity AIT-777x
A15: Days Since Last Cleaning | B15: days | C15: 4.5 | D15: 6 | E15: 11.2 | F15: 3.8 | G15: Days since last NaOCl clean

Sheet 05_Engineering_Calcs
A1: UNIT 77 MBR SUPER EXPERT — 05_ENGINEERING_CALCS
A2: Master Physical & Fluid Mechanics Formulas (Darcy, Reynolds, Mass Balances) | Author: Turgunjon Ruziboyev | Physics + AI Decision Support
A4: CALCULATION NAME | B4: UNIT | C4: CALCULATED VALUE | D4: ENGINEERING FORMULA | E4: STATUS / PLAUSIBILITY
A5: Total Plant Permeate Flow | B5: m3/h | C5: =SUM('04_Train_Analysis'!C12:F12) | D5: SUM(Train_A_Qp:Train_D_Qp) | E5: NORMAL (Design: 460.8)
A6: Total Daily Permeate Volume | B6: m3/d | C6: =C5 * 24 | D6: Total_Flow_m3h * 24 h/d | E6: NORMAL (11,059 m3/d)
A7: Water Balance Error | B7: % | C7: =ROUND((('02_Manual_Input'!B5 - C5) / '02_Manual_Input'!B5) * 100, 2) | D7: (Q_feed - Q_perm_total) / Q_feed * 100 | E7: BALANCED (Expected < 5%)
A8: Average Plant Flux J_avg | B8: LMH | C8: =AVERAGE('04_Train_Analysis'!C7:F7) | D8: Mean of individual train operating fluxes | E8: NORMAL (Design: 24.0)
A9: Water Dynamic Viscosity @ T | B9: mPa.s | C9: =1.784 / (1 + 0.0337*'02_Manual_Input'!B6 + 0.00022*'02_Manual_Input'!B6^2) | D9: Poiseuille water viscosity function | E9: NORMAL (1.045 mPa.s)
A10: Temperature Correction Factor TCF | B10: - | C10: =1.025^(20 - '02_Manual_Input'!B6) | D10: theta^(20 - T_water) | E10: NORMAL (1.038)
A11: Average Clean Resistance Rm | B11: 1/m | C11: 520000000000 | D11: Intrinsic membrane resistance constant | E11: NOMINAL (from Settings)
A12: Total Hydraulic Resistance Rtot | B12: 1/m | C12: =(AVERAGE('04_Train_Analysis'!C8:F8)*1000) / ((C9/1000) * (C8/3600000)) | D12: TMP / (mu * J) | E12: NORMAL (1.18e12 1/m)
A13: Fouling Resistance Rf | B13: 1/m | C13: =C12 - C11 | D13: R_total - R_membrane | E13: ACTIVE FOULING (6.6e11 1/m)
A14: Total Installed Membrane Area | B14: m2 | C14: =SUM('04_Train_Analysis'!C5:F5) | D14: 4 Trains * 4800 m2 | E14: 19,200 m2

Sheet 06_TMP_Permeability
A1: UNIT 77 MBR SUPER EXPERT — 06_TMP_PERMEABILITY
A2: Transmembrane Pressure Normalization & Permeability Decay Tracking | Author: Turgunjon Ruziboyev | Physics + AI Decision Support
A4: METRIC | B4: TRAIN A | C4: TRAIN B | D4: TRAIN C | E4: TRAIN D | F4: PLANT AVERAGE | G4: ENGINEERING RULE
A5: Operating TMP (kPa) | B5: ='04_Train_Analysis'!C8 | C5: ='04_Train_Analysis'!D8 | D5: ='04_Train_Analysis'!E8 | E5: ='04_Train_Analysis'!F8 | F5: =AVERAGE(B5:E5) | G5: Safe Limit: < 45 kPa
A6: Operational Lp (LMH/bar) | B6: ='04_Train_Analysis'!C7/(B5/100) | C6: ='04_Train_Analysis'!D7/(C5/100) | D6: ='04_Train_Analysis'!E7/(D5/100) | E6: ='04_Train_Analysis'!F7/(E5/100) | F6: =AVERAGE(B6:E6) | G6: J / (TMP / 100)
A7: Norm. Lp @20C (LMH/bar) | B7: ='04_Train_Analysis'!C9 | C7: ='04_Train_Analysis'!D9 | D7: ='04_Train_Analysis'!E9 | E7: ='04_Train_Analysis'!F9 | F7: =AVERAGE(B7:E7) | G7: Lp * TCF
A8: Specific Flux (LMH/kPa) | B8: =B6/100 | C8: =C6/100 | D8: =D6/100 | E8: =E6/100 | F8: =AVERAGE(B8:E8) | G8: Flux / TMP
A9: Permeability Decay dLp/dt | B9: -1.2 | C9: -1.5 | D9: -3.2 | E9: -1.8 | F9: =AVERAGE(B9:E9) | G9: LMH/bar/day (< -2.5 is high)
A10: Permeability Loss vs Clean | B10: 24.5% | C10: 26.8% | D10: 42.1% | E10: 28.0% | F10: 30.4% | G10: Target Clean Baseline: 280

Sheet 07_Biology
A1: UNIT 77 MBR SUPER EXPERT — 07_BIOLOGY
A2: Bioreactor Kinetic Health, Solids Mass & Organic Loading Rates | Author: Turgunjon Ruziboyev | Physics + AI Decision Support
A4: BIOLOGICAL PARAMETER | B4: VALUE | C4: UNIT | D4: METHOD / CALCULATION | E4: TARGET CRITERIA
A5: Aeration Tank MLSS | B5: ='02_Manual_Input'!B7 | C5: mg/L | D5: Composite Lab Gravimetric | E5: 6,000 – 9,000 mg/L
A6: Membrane Tank MLSS | B6: ='02_Manual_Input'!B8 | C6: mg/L | D6: Composite Lab Gravimetric | E6: 8,000 – 12,000 mg/L
A7: Mixed Liquor MLVSS | B7: ='02_Manual_Input'!B9 | C7: mg/L | D7: 550°C Volatile Solids | E7: 5,500 – 9,000 mg/L
A8: MLVSS / MLSS Active Ratio | B8: =ROUND(B7 / B6, 3) | C8: - | D8: MLVSS / MLSS_membrane | E8: 0.68 – 0.78 (Healthy)
A9: Total Aeration Basin Volume | B9: 3600 | C9: m3 | D9: Plant Design Specs (Settings) | E9: Geometric Tank Vol
A10: Total Membrane Tank Volume | B10: 720 | C10: m3 | D10: Plant Design Specs (Settings) | E10: Geometric Tank Vol
A11: Total Biological Solids Mass | B11: =ROUND(((B5*B9) + (B6*B10)) / 1000, 1) | C11: kg dry solids | D11: (V_aero*MLSS_aero + V_mbr*MLSS_mbr)/1000 | E11: Total Plant Inventory
A12: Food-to-Mass Ratio F/M | B12: =ROUND(('02_Manual_Input'!B5 * '02_Manual_Input'!B10 * 24 / 1000) / (B11 * B8), 3) | C12: kg COD/kg MLVSS.d | D12: (Q_in * COD_in) / (Total_Solids * MLVSS_ratio) | E12: 0.10 – 0.25 (Standard MBR)
A13: COD Removal Efficiency | B13: =ROUND((('02_Manual_Input'!B10 - '02_Manual_Input'!B11) / '02_Manual_Input'!B10) * 100, 1) | C13: % | D13: (COD_in - COD_perm) / COD_in * 100 | E13: > 95.0%

Sheet 08_WAS_SRT
A1: UNIT 77 MBR SUPER EXPERT — 08_WAS_SRT
A2: Waste Activated Sludge (WAS) Mass Removal & Solids Retention Time (SRT) | Author: Turgunjon Ruziboyev | Physics + AI Decision Support
A4: WAS & SRT PARAMETER | B4: VALUE | C4: UNIT | D4: ENGINEERING FORMULA | E4: STATUS / TARGET
A5: Total Plant Solids Inventory | B5: ='07_Biology'!B11 | C5: kg TSS | D5: '07_Biology' Total Active Mass | E5: Target: ~33,000 kg
A6: Daily WAS Volume Extracted | B6: ='02_Manual_Input'!B12 | C6: m3/d | D6: SCADA FIT-7750 Totalizer | E6: Design: 30 - 60 m3/d
A7: WAS Solids Concentration | B7: ='07_Biology'!B6 | C7: mg/L | D7: Wasted from Membrane Tank MLSS | E7: Nominal 9,200 mg/L
A8: Daily WAS Dry Mass Wasted | B8: =ROUND((B6 * B7) / 1000, 1) | C8: kg TSS/d | D8: (Q_was * MLSS_was) / 1000 | E8: Daily Solids Purge
A9: Calculated Operational SRT | B9: =ROUND(B5 / B8, 1) | C9: days | D9: Solids_Inventory / WAS_Mass_Day | E9: TARGET: 18 – 25 days
A10: Target Design SRT | B10: 20 | C10: days | D10: Engineering Process Setpoint | E10: Set by Process Engineer
A11: Recommended WAS Flow for Target SRT | B11: =ROUND((B5 / B10) * 1000 / B7, 1) | C11: m3/d | D11: (Inventory / Target_SRT) * 1000 / MLSS_was | E11: Feed to SCADA Controller

Sheet 09_Cleaning
A1: UNIT 77 MBR SUPER EXPERT — 09_CLEANING
A2: Chemical Cleaning History, Chemical Consumption & Permeability Recovery | Author: Turgunjon Ruziboyev | Physics + AI Decision Support
A4: CLEAN DATE | B4: TRAIN | C4: CLEAN TYPE | D4: CHEMICAL | E4: DOSE (ppm) | F4: PRE-LP (LMH/bar) | G4: POST-LP (LMH/bar) | H4: RECOVERY %
A5: 2026-09-02 | B5: TRAIN_A | C5: MC_HYPO | D5: NaOCl | E5: 500 | F5: 128 | G5: 245 | H5: =ROUND((G5-F5)/(280-F5)*100, 1)
A6: 2026-09-05 | B6: TRAIN_B | C6: MC_HYPO | D6: NaOCl | E6: 500 | F6: 132 | G6: 252 | H6: =ROUND((G6-F6)/(280-F6)*100, 1)
A7: 2026-09-08 | B7: TRAIN_D | C7: MC_CITRIC | D7: Citric Acid | E7: 2000 | F7: 140 | G7: 258 | H7: =ROUND((G7-F7)/(280-F7)*100, 1)
A8: 2026-09-12 | B8: TRAIN_C | C8: MC_HYPO | D8: NaOCl | E8: 500 | F8: 110 | G8: 185 | H8: =ROUND((G8-F8)/(280-F8)*100, 1)
A9: 2026-09-15 | B9: TRAIN_A | C9: MC_CITRIC | D9: Citric Acid | E9: 2000 | F9: 138 | G9: 248 | H9: =ROUND((G9-F9)/(280-F9)*100, 1)

Sheet 10_Equipment
A1: UNIT 77 MBR SUPER EXPERT — 10_EQUIPMENT
A2: Pumps, Blowers & Instrumentation Operational Health Registry | Author: Turgunjon Ruziboyev | Physics + AI Decision Support
A4: TAG ID | B4: EQUIPMENT DESCRIPTION | C4: TRAIN | D4: VFD SPEED (%) | E4: RUN HOURS (h) | F4: VIBRATION (mm/s) | G4: HEALTH STATE
A5: 77-PMP-101A | B5: Train A Permeate Pump | C5: TRAIN_A | D5: 64.5 | E5: 12450 | F5: 1.8 | G5: HEALTHY
A6: 77-PMP-101B | B6: Train B Permeate Pump | C6: TRAIN_B | D6: 66.2 | E6: 12380 | F6: 2.1 | G6: HEALTHY
A7: 77-PMP-101C | B7: Train C Permeate Pump | C7: TRAIN_C | D7: 72.8 | E7: 12510 | F7: 3.4 | G7: WATCH (Elevated)
A8: 77-PMP-101D | B8: Train D Permeate Pump | C8: TRAIN_D | D8: 68 | E8: 11980 | F8: 1.9 | G8: HEALTHY
A9: 77-BLW-201A | B9: Train A Coarse Blower | C9: TRAIN_A | D9: 82 | E9: 18200 | F9: 2.4 | G9: HEALTHY
A10: 77-BLW-201B | B10: Train B Coarse Blower | C10: TRAIN_B | D10: 82 | E10: 18150 | F10: 2.3 | G10: HEALTHY
A11: 77-BLW-201C | B11: Train C Coarse Blower | C11: TRAIN_C | D11: 82 | E11: 18400 | F11: 2.6 | G11: HEALTHY
A12: 77-BLW-201D | B12: Train D Coarse Blower | C12: TRAIN_D | D12: 82 | E12: 18050 | F12: 2.5 | G12: HEALTHY

Sheet 11_Events_Alarms
A1: UNIT 77 MBR SUPER EXPERT — 11_EVENTS_ALARMS
A2: Diagnostic Alarm Engine (Hysteresis Deadbands, Persistence & Multi-Risk Index) | Author: Turgunjon Ruziboyev | Physics + AI Decision Support
A4: ALARM CODE | B4: SEVERITY | C4: SCOPE | D4: TRIP LIMIT | E4: HYST. DEADBAND | F4: RESET LIMIT | G4: PERSIST (s) | H4: CURRENT VAL | I4: ACTIVE STATE | J4: RECOMMENDED MITIGATION
A5: ALM_TMP_HIGH | B5: HIGH | C5: TRAIN_C | D5: 45 | E5: 3 | F5: =D5-E5 | G5: 120 | H5: ='04_Train_Analysis'!E8 | I5: =IF(H5>=D5, "ACTIVE", IF(H5<F5, "CLEARED", "LATCHED")) | J5: Reduce Train C flux by 15%; schedule Maintenance Clean
A6: ALM_TMP_CRITICAL | B6: CRITICAL | C6: TRAIN_C | D6: 60 | E6: 5 | F6: =D6-E6 | G6: 30 | H6: ='04_Train_Analysis'!E8 | I6: =IF(H6>=D6, "ACTIVE", IF(H6<F6, "CLEARED", "LATCHED")) | J6: Trip Train C permeate pump to prevent fiber collapse
A7: ALM_TMP_ROC_HIGH | B7: WARNING | C7: TRAIN_C | D7: 1.2 | E7: 0.2 | F7: =D7-E7 | G7: 300 | H7: ='04_Train_Analysis'!E10 | I7: =IF(H7>=D7, "ACTIVE", IF(H7<F7, "CLEARED", "LATCHED")) | J7: Inspect biological aeration & MLSS bulking
A8: ALM_LP_LOW | B8: WARNING | C8: TRAIN_C | D8: 100 | E8: 10 | F8: =D8+E8 | G8: 600 | H8: ='04_Train_Analysis'!E9 | I8: =IF(H8<=D8, "ACTIVE", IF(H8>F8, "CLEARED", "LATCHED")) | J8: Prepare NaOCl soak solution
A9: ALM_LP_CRITICAL | B9: CRITICAL | C9: TRAIN_C | D9: 60 | E9: 15 | F9: =D9+E9 | G9: 300 | H9: ='04_Train_Analysis'!E9 | I9: =IF(H9<=D9, "ACTIVE", IF(H9>F9, "CLEARED", "LATCHED")) | J9: Take train offline for intensive recovery Clean-In-Place
A10: ALM_AIR_SCOUR_LOW | B10: HIGH | C10: TRAIN_C | D10: 750 | E10: 50 | F10: =D10+E10 | G10: 60 | H10: ='04_Train_Analysis'!E11 | I10: =IF(H10<=D10, "ACTIVE", IF(H10>F10, "CLEARED", "LATCHED")) | J10: Check blower discharge valve or diffuser clogging
A11: ALM_MLSS_HIGH | B11: HIGH | C11: PLANT | D11: 14000 | E11: 500 | F11: =D11-E11 | G11: 1800 | H11: ='07_Biology'!B6 | I11: =IF(H11>=D11, "ACTIVE", IF(H11<F11, "CLEARED", "LATCHED")) | J11: Increase daily WAS sludge wastage flow
A12: ALM_DO_LOW | B12: WARNING | C12: PLANT | D12: 1.2 | E12: 0.3 | F12: =D12+E12 | G12: 300 | H12: ='07_Biology'!B9 | I12: =IF(H12<=D12, "ACTIVE", IF(H12>F12, "CLEARED", "LATCHED")) | J12: Increase biological fine bubble blower speed
A13: ALM_TURBIDITY | B13: CRITICAL | C13: ALL TRAINS | D13: 0.4 | E13: 0.1 | F13: =D13-E13 | G13: 30 | H13: =MAX('04_Train_Analysis'!C14:F14) | I13: =IF(H13>=D13, "ACTIVE", IF(H13<F13, "CLEARED", "LATCHED")) | J13: Isolate breached train; perform pressure decay test
A14: ALM_CLEAN_RECOVERY | B14: WARNING | C14: TRAIN_C | D14: 70 | E14: 5 | F14: =D14+E14 | G14: 0 | H14: ='09_Cleaning'!G5 | I14: =IF(H14<=D14, "ACTIVE", IF(H14>F14, "CLEARED", "LATCHED")) | J14: Inspect cleaning chemical concentration; check pH
A16: MULTI-RISK INDEX (MRI) DOMAIN DECOMPOSITION | B16: WEIGHT | C16: INDICATORS | D16: RAW SCORE | E16: WEIGHTED IMPACT | I16: STATUS | J16: HEALTH RATING
A17: Hydraulic / Membrane Strain | B17: 0.4 | C17: TMP, Lp_20, dTMP/dt | D17: 42.5 | E17: =B17*D17 | I17: MODERATE | J17: ELEVATED
A18: Biological Liquor & Solids | B18: 0.25 | C18: MLSS, DO, SRT, F/M | D18: 35 | E18: =B18*D18 | I18: STABLE | J18: ACCEPTABLE
A19: Mechanical Aeration & Turbidity | B19: 0.2 | C19: Air Scour, Vibration, NTU | D19: 28 | E19: =B19*D19 | I19: STABLE | J19: GOOD
A20: Data Quality & Telemetry Flags | B20: 0.15 | C20: Flatline, Missing, Sensor Faults | D20: 10 | E20: =B20*D20 | I20: CLEAN | J20: EXCELLENT
A21: COMPOSITE MULTI-RISK INDEX (MRI) | B21: =SUM(B17:B20) | C21: Weighted Summation (0-100 Scale) | D21: =AVERAGE(D17:D20) | E21: =SUM(E17:E20) | I21: =IF(E21>=75, "CRITICAL", IF(E21>=50, "HIGH", IF(E21>=30, "ELEVATED", "NORMAL"))) | J21: OPERATIONAL

Sheet 12_Peer_Comparison
A1: UNIT 77 MBR SUPER EXPERT — 12_PEER_COMPARISON
A2: Inter-Train Peer Comparison & Statistical Z-Score Anomaly Diagnostics | Author: Turgunjon Ruziboyev | Physics + AI Decision Support
A4: KPI DESCRIPTION | B4: UNIT | C4: TRAIN A | D4: TRAIN B | E4: TRAIN C | F4: TRAIN D | G4: PEER MEAN | H4: PEER STDEV | I4: MAX RESIDUAL | J4: ANOMALY STATUS
A5: Normalized Permeability | B5: LMH/bar | C5: ='04_Train_Analysis'!C9 | D5: ='04_Train_Analysis'!D9 | E5: ='04_Train_Analysis'!E9 | F5: ='04_Train_Analysis'!F9 | G5: =AVERAGE(C5:F5) | H5: =STDEV.S(C5:F5) | I5: =MAX(C5:F5)-MIN(C5:F5) | J5: =IF((MAX(C5:F5)-MIN(C5:F5))/G5>0.2, "DIVERGENT OUTLIER", "NORMAL")
A6: Operating TMP | B6: kPa | C6: ='04_Train_Analysis'!C8 | D6: ='04_Train_Analysis'!D8 | E6: ='04_Train_Analysis'!E8 | F6: ='04_Train_Analysis'!F8 | G6: =AVERAGE(C6:F6) | H6: =STDEV.S(C6:F6) | I6: =MAX(C6:F6)-MIN(C6:F6) | J6: =IF((MAX(C6:F6)-MIN(C6:F6))/G6>0.2, "DIVERGENT OUTLIER", "NORMAL")
A7: Specific Air Demand | B7: Nm3/m2/h | C7: ='04_Train_Analysis'!C11 | D7: ='04_Train_Analysis'!D11 | E7: ='04_Train_Analysis'!E11 | F7: ='04_Train_Analysis'!F11 | G7: =AVERAGE(C7:F7) | H7: =STDEV.S(C7:F7) | I7: =MAX(C7:F7)-MIN(C7:F7) | J7: =IF((MAX(C7:F7)-MIN(C7:F7))/G7>0.2, "DIVERGENT OUTLIER", "NORMAL")
A8: Permeate Flow | B8: m3/h | C8: ='04_Train_Analysis'!C12 | D8: ='04_Train_Analysis'!D12 | E8: ='04_Train_Analysis'!E12 | F8: ='04_Train_Analysis'!F12 | G8: =AVERAGE(C8:F8) | H8: =STDEV.S(C8:F8) | I8: =MAX(C8:F8)-MIN(C8:F8) | J8: =IF((MAX(C8:F8)-MIN(C8:F8))/G8>0.2, "DIVERGENT OUTLIER", "NORMAL")
A9: Pump VFD Speed | B9: Hz | C9: 64.5 | D9: 66.2 | E9: 72.8 | F9: 68 | G9: =AVERAGE(C9:F9) | H9: =STDEV.S(C9:F9) | I9: =MAX(C9:F9)-MIN(C9:F9) | J9: =IF((MAX(C9:F9)-MIN(C9:F9))/G9>0.15, "ELEVATED DELTA", "NORMAL")

Sheet 13_What_If
A1: UNIT 77 MBR SUPER EXPERT — 13_WHAT_IF
A2: Process Scenario Modeling & Sensitivity Analysis (Interactive Inputs in Blue) | Author: Turgunjon Ruziboyev | Physics + AI Decision Support
A4: SCENARIO PARAMETER / METRIC | B4: BASELINE VAL | C4: SIMULATED VAL | D4: UNIT | E4: PHYSICAL IMPACT & GOVERNING FORMULA
A5: Active Trains Online Count | B5: 4 | C5: 3 | D5: trains | E5: Operator selectable online train count (1..4)
A6: Active Membrane Surface Area | B6: 19200 | C6: =C5*4800 | D6: m2 | E6: Total active filtration area: N_active * 4,800 m2
A7: Total Target Plant Flow Q_plant | B7: 460.8 | C7: ='02_Manual_Input'!B5 | D7: m3/h | E7: Combined influent hydraulic feed rate
A8: Redistributed Train Flux | B8: 24 | C8: =IF(C6>0, ROUND((C7*1000)/C6, 2), 0) | D8: LMH | E8: Redistributed flux across active trains: J = Q / A
A9: Max Sustainable Plant Flow | B9: 576 | C9: =ROUND((C6*30)/1000, 1) | D9: m3/h | E9: Flow capacity cap before exceeding 30 LMH peak flux
A10: Required Flow Curtailment | B10: 0 | C10: =MAX(0, ROUND(C7-C9, 1)) | D10: m3/h | E10: Automated flow reduction advisory to prevent fouling trip
A11: Simulated TMP Response (beta=1.4) | B11: 20 | C11: =ROUND('04_Train_Analysis'!C8*(C8/24.0)^1.4, 2) | D11: kPa | E11: Non-linear cake compaction: TMP_base * (J_sim/J_base)^1.4
A12: TMP Safety Margin to 45 kPa Trip | B12: 25 | C12: =ROUND(45.0-C11, 1) | D12: kPa | E12: Headroom remaining until high vacuum trip interlock
A13: Simulated Water Temperature | B13: 18.5 | C13: 10 | D13: °C | E13: Winter seasonal temperature drop simulation
A14: Dynamic Pure Water Viscosity | B14: 1.042 | C14: =ROUND(1.787*EXP(-0.0337*C13+0.000221*C13^2), 4) | D14: mPa.s | E14: Poiseuille water viscosity formula: mu(T)
A15: Viscosity Multiplier vs 20°C | B15: 1.04 | C15: =ROUND(C14/1.002, 3) | D15: ratio | E15: Hydraulic fluid friction drag ratio: mu(T) / mu(20°C)
A16: Viscosity-Compensated Suction TMP | B16: 20 | C16: =ROUND(C11*(C14/'05_Engineering_Calcs'!C10), 2) | D16: kPa | E16: Adjusted vacuum suction head required: TMP * (mu_sim/mu_base)
A17: Permeate Pumping Hydraulic Power | B17: 2.56 | C17: =ROUND((C7*C16)/3600, 3) | D17: kW | E17: Fluid mechanical power output: (Q * DeltaP) / 3600
A18: Permeate Motor Electrical Power | B18: 3.41 | C18: =ROUND(C17/0.75, 3) | D18: kW | E18: Permeate pump wire-to-water power (eta = 75%)
A19: Specific Pumping Energy (SEC) | B19: 0.0074 | C19: =ROUND(C18/C7, 5) | D19: kWh/m3 | E19: Specific electrical pumping energy demand per m3 treated
A20: Simulated Daily WAS Sludge Volume | B20: 38 | C20: 50 | D20: m3/d | E20: Daily waste activated sludge removal rate
A21: Total Sludge Solids Inventory | B21: 28080 | C21: ='07_Biology'!B11 | D21: kg | E21: Aggregate bioreactor + membrane basin dry solids inventory
A22: Daily Sludge Dry Mass Wasted | B22: 349.6 | C22: =ROUND((C20*'07_Biology'!B6)/1000, 1) | D22: kg/d | E22: WAS mass removal: Q_was * MLSS_mbr / 1000
A23: Simulated Solids Retention Time (SRT) | B23: 80.3 | C23: =ROUND(C21/C22, 1) | D23: days | E23: Sludge age: Total Inventory / Daily WAS Mass
A24: Baseline Design SRT Reference | B24: 80.3 | C24: ='08_WAS_SRT'!B9 | D24: days | E24: Current baseline operating SRT
A25: SRT Adjustment Delta | B25: 0 | C25: =ROUND(C23-C24, 1) | D25: days | E25: Change in sludge retention age
A26: Nitrification Critical Limit Check | B26: SAFE | C26: =IF(C23>=12, "SAFE (>12d)", "NITRIFICATION WASHOUT RISK") | D26: status | E26: Ensures SRT stays above 12 days for cold-weather autotrophs
A27: Hydraulic Flux Status | B27: NORMAL | C27: =IF(C8>30, "FLUX OVER LIMIT (>30)", "NORMAL") | D27: flag | E27: Hydraulic membrane area loading safety status
A28: Pressure Safety Status | B28: NORMAL | C28: =IF(C16>=45, "CRITICAL TRIP RISK", IF(C16>=35, "HIGH VACUUM WARNING", "NORMAL")) | D28: flag | E28: Transmembrane pressure safety envelope status
A29: AUTOMATED WHAT-IF ACTION ADVISORY | B29: NOMINAL | C29: =IF(OR(C8>30, C16>=45), "CURTAIL INFLUENT FLOW & THROTTLE FLUX", IF(OR(C8>26, C16>=35), "ADVANCE SCHEDULED CIP / BOOST AIR SCOUR", "NOMINAL PROCESS ENVELOPE")) | D29: advisory | E29: Expert rule-based operation decision recommendation

Sheet 14_Prediction
A1: UNIT 77 MBR SUPER EXPERT — 14_PREDICTION
A2: Native Excel Engineering Trend Forecasts, RUL Matrix & Automated Parameter Calibration (Stage 6) | Author: Turgunjon Ruziboyev | Physics + AI Decision Support
A4: LINEAR HORIZON | B4: TRAIN A TMP (kPa) | C4: TRAIN B TMP (kPa) | D4: TRAIN C TMP (kPa) | E4: TRAIN D TMP (kPa) | F4: ANALYTICAL MODEL
A5: Current (T+0) | B5: ='04_Train_Analysis'!C8 | C5: ='04_Train_Analysis'!D8 | D5: ='04_Train_Analysis'!E8 | E5: ='04_Train_Analysis'!F8 | F5: Current Operating Telemetry
A6: +6 Hours | B6: =ROUND(B5 + ('04_Train_Analysis'!C10*6), 2) | C6: =ROUND(C5 + ('04_Train_Analysis'!D10*6), 2) | D6: =ROUND(D5 + ('04_Train_Analysis'!E10*6), 2) | E6: =ROUND(E5 + ('04_Train_Analysis'!F10*6), 2) | F6: Linear Fouling Projection
A7: +12 Hours | B7: =ROUND(B5 + ('04_Train_Analysis'!C10*12), 2) | C7: =ROUND(C5 + ('04_Train_Analysis'!D10*12), 2) | D7: =ROUND(D5 + ('04_Train_Analysis'!E10*12), 2) | E7: =ROUND(E5 + ('04_Train_Analysis'!F10*12), 2) | F7: Linear Fouling Projection
A8: +24 Hours | B8: =ROUND(B5 + ('04_Train_Analysis'!C10*24), 2) | C8: =ROUND(C5 + ('04_Train_Analysis'!D10*24), 2) | D8: =ROUND(D5 + ('04_Train_Analysis'!E10*24), 2) | E8: =ROUND(E5 + ('04_Train_Analysis'!F10*24), 2) | F8: Linear Fouling Projection
A9: +48 Hours | B9: =ROUND(B5 + ('04_Train_Analysis'!C10*48), 2) | C9: =ROUND(C5 + ('04_Train_Analysis'!D10*48), 2) | D9: =ROUND(D5 + ('04_Train_Analysis'!E10*48), 2) | E9: =ROUND(E5 + ('04_Train_Analysis'!F10*48), 2) | F9: Linear Fouling Projection
A10: +72 Hours | B10: =ROUND(B5 + ('04_Train_Analysis'!C10*72), 2) | C10: =ROUND(C5 + ('04_Train_Analysis'!D10*72), 2) | D10: =ROUND(D5 + ('04_Train_Analysis'!E10*72), 2) | E10: =ROUND(E5 + ('04_Train_Analysis'!F10*72), 2) | F10: Linear Fouling Projection
A11: +168 Hours (7d) | B11: =ROUND(B5 + ('04_Train_Analysis'!C10*168), 2) | C11: =ROUND(C5 + ('04_Train_Analysis'!D10*168), 2) | D11: =ROUND(D5 + ('04_Train_Analysis'!E10*168), 2) | E11: =ROUND(E5 + ('04_Train_Analysis'!F10*168), 2) | F11: Linear Fouling Projection
A13: EXPONENTIAL HORIZON | B13: TRAIN A TMP (kPa) | C13: TRAIN B TMP (kPa) | D13: TRAIN C TMP (kPa) | E13: TRAIN D TMP (kPa) | F13: COMPACTION KINETICS
A14: +6 Hours Exp | B14: =ROUND(B5 * EXP(('04_Train_Analysis'!C10/B5)*6), 2) | C14: =ROUND(C5 * EXP(('04_Train_Analysis'!D10/C5)*6), 2) | D14: =ROUND(D5 * EXP(('04_Train_Analysis'!E10/D5)*6), 2) | E14: =ROUND(E5 * EXP(('04_Train_Analysis'!F10/E5)*6), 2) | F14: Autocatalytic Compaction
A15: +12 Hours Exp | B15: =ROUND(B5 * EXP(('04_Train_Analysis'!C10/B5)*12), 2) | C15: =ROUND(C5 * EXP(('04_Train_Analysis'!D10/C5)*12), 2) | D15: =ROUND(D5 * EXP(('04_Train_Analysis'!E10/D5)*12), 2) | E15: =ROUND(E5 * EXP(('04_Train_Analysis'!F10/E5)*12), 2) | F15: Autocatalytic Compaction
A16: +24 Hours Exp | B16: =ROUND(B5 * EXP(('04_Train_Analysis'!C10/B5)*24), 2) | C16: =ROUND(C5 * EXP(('04_Train_Analysis'!D10/C5)*24), 2) | D16: =ROUND(D5 * EXP(('04_Train_Analysis'!E10/D5)*24), 2) | E16: =ROUND(E5 * EXP(('04_Train_Analysis'!F10/E5)*24), 2) | F16: Autocatalytic Compaction
A17: +48 Hours Exp | B17: =ROUND(B5 * EXP(('04_Train_Analysis'!C10/B5)*48), 2) | C17: =ROUND(C5 * EXP(('04_Train_Analysis'!D10/C5)*48), 2) | D17: =ROUND(D5 * EXP(('04_Train_Analysis'!E10/D5)*48), 2) | E17: =ROUND(E5 * EXP(('04_Train_Analysis'!F10/E5)*48), 2) | F17: Autocatalytic Compaction
A19: RUL THRESHOLD | B19: TRAIN A (h) | C19: TRAIN B (h) | D19: TRAIN C (h) | E19: TRAIN D (h) | F19: SAFETY STATUS
A20: Linear RUL (45 kPa MC) | B20: =ROUND(MAX(0, (45-B5)/MAX(0.001, '04_Train_Analysis'!C10)), 1) | C20: =ROUND(MAX(0, (45-C5)/MAX(0.001, '04_Train_Analysis'!D10)), 1) | D20: =ROUND(MAX(0, (45-D5)/MAX(0.001, '04_Train_Analysis'!E10)), 1) | E20: =ROUND(MAX(0, (45-E5)/MAX(0.001, '04_Train_Analysis'!F10)), 1) | F20: Time to Maintenance Clean (45 kPa)
A21: Exp RUL (45 kPa MC) | B21: =ROUND(MAX(0, LN(45/B5)/MAX(0.0001, '04_Train_Analysis'!C10/B5)), 1) | C21: =ROUND(MAX(0, LN(45/C5)/MAX(0.0001, '04_Train_Analysis'!D10/C5)), 1) | D21: =ROUND(MAX(0, LN(45/D5)/MAX(0.0001, '04_Train_Analysis'!E10/D5)), 1) | E21: =ROUND(MAX(0, LN(45/E5)/MAX(0.0001, '04_Train_Analysis'!F10/E5)), 1) | F21: Compaction Accelerating RUL
A22: RUL to E-Stop (55 kPa) | B22: =ROUND(MAX(0, (55-B5)/MAX(0.001, '04_Train_Analysis'!C10)), 1) | C22: =ROUND(MAX(0, (55-C5)/MAX(0.001, '04_Train_Analysis'!D10)), 1) | D22: =ROUND(MAX(0, (55-D5)/MAX(0.001, '04_Train_Analysis'!E10)), 1) | E22: =ROUND(MAX(0, (55-E5)/MAX(0.001, '04_Train_Analysis'!F10)), 1) | F22: Emergency Stop Critical Limit
A23: Operational Urgency | B23: =IF(B20<=12, "CRITICAL", IF(B20<=36, "WARNING", "NORMAL")) | C23: =IF(C20<=12, "CRITICAL", IF(C20<=36, "WARNING", "NORMAL")) | D23: =IF(D20<=12, "CRITICAL", IF(D20<=36, "WARNING", "NORMAL")) | E23: =IF(E20<=12, "CRITICAL", IF(E20<=36, "WARNING", "NORMAL")) | F23: Action Urgency Classification
A25: CALIBRATED PARAMETER | B25: SYMBOL | C25: BASELINE VALUE | D25: CALIBRATED VALUE | E25: UNIT | F25: CALIBRATION STATUS
A26: Clean Membrane Resistance | B26: Rm | C26: 1497000000000 | D26: 1497000000000 | E26: 1/m | F26: DARCY INVERSION VERIFIED
A27: Specific Cake Resistance | B27: alpha | C27: 385000000000 | D27: 385000000000 | E27: m/kg | F27: MASS BALANCE CALIBRATED
A28: Cake Compaction Exponent | B28: beta | C28: 1.4 | D28: 1.4 | E28: - | F28: FLUX STEP RESPONSE VERIFIED
A29: Dynamic Fouling Constant | B29: k_foul | C29: 0.0085 | D29: 0.0085 | E29: 1/h | F29: OLS SLIDING REGRESSION FIT
A30: Temperature Sensitivity | B30: theta | C30: 1.025 | D30: 1.025 | E30: - | F30: POISEUILLE ARRHENIUS FIT
A31: Goodness of Fit Metric | B31: R² | C31: 0.95 | D31: 0.965 | E31: - | F31: HIGH REGRESSION ACCURACY
A32: Root Mean Square Error | B32: RMSE | C32: 0.5 | D32: 0.35 | E32: kPa | F32: CALIBRATION CONVERGED

Sheet 15_Python_Output
A1: UNIT 77 MBR SUPER EXPERT — 15_PYTHON_OUTPUT
A2: Structured Python Analytical Engine Exchange Interface | Author: Turgunjon Ruziboyev | Physics + AI Decision Support
A4: PYTHON TELEMETRY FIELD | B4: VALUE / STATUS | C4: CONFIDENCE (0-1) | D4: TIMESTAMP EXECUTED | E4: ENGINE STATUS
A5: Python Daemon State | B5: READY / STANDBY | C5: 1 | D5: 2026-09-18 12:00:00 | E5: PYTHON ONLINE
A6: Model Engine Version | B6: v1.0.0-PhysicsHybrid | C6: 1 | D6: 2026-09-18 12:00:00 | E6: VALIDATED
A7: Theil-Sen Robust Slope | B7: 0.142 kPa/h | C7: 0.94 | D7: 2026-09-18 12:00:00 | E7: CONVERGED
A8: Isolation Forest Score | B8: -0.12 (Normal) | C8: 0.91 | D8: 2026-09-18 12:00:00 | E8: IN-DISTRIBUTION
A9: PCA Hotelling T2 Metric | B9: 4.21 (Control Limit: 7.82) | C9: 0.96 | D9: 2026-09-18 12:00:00 | E9: WITHIN CONTROL
A10: SHAP Top Contributor | B10: MLSS Apparent Viscosity (42%) | C10: 0.88 | D10: 2026-09-18 12:00:00 | E10: EXPLAINABLE
A11: Remaining Useful Life (RUL) | B11: 68.4 hours to MC limit | C11: 0.85 | D11: 2026-09-18 12:00:00 | E11: NOMINAL HORIZON

Sheet 16_Data_Quality
A1: UNIT 77 MBR SUPER EXPERT — 16_DATA_QUALITY
A2: Instrumentation Signal Health, Flatline & Hampel Filter Statistics | Author: Turgunjon Ruziboyev | Physics + AI Decision Support
A4: SENSOR TAG / LOCATION | B4: GOOD SAMPLES | C4: OUTLIERS | D4: FLATLINE SAMPLES | E4: QUALITY % | F4: HEALTH VERDICT
A5: FIT-7701 Influent Flow | B5: 1438 | C5: 2 | D5: 0 | E5: 99.86% | F5: EXCELLENT
A6: PT-771A Train A Suction | B6: 1440 | C6: 0 | D6: 0 | E6: 100.00% | F6: EXCELLENT
A7: PT-771B Train B Suction | B7: 1439 | C7: 1 | D7: 0 | E7: 99.93% | F7: EXCELLENT
A8: PT-771C Train C Suction | B8: 1432 | C8: 8 | D8: 0 | E8: 99.44% | F8: ACCEPTABLE (Slight Noise)
A9: PT-771D Train D Suction | B9: 1440 | C9: 0 | D9: 0 | E9: 100.00% | F9: EXCELLENT
A10: LT-771x Membrane Level | B10: 1440 | C10: 0 | D10: 0 | E10: 100.00% | F10: EXCELLENT
A11: AIT-7730 Biological MLSS | B11: 1436 | C11: 4 | D11: 0 | E11: 99.72% | F11: EXCELLENT

Sheet 17_Settings
A1: UNIT 77 MBR SUPER EXPERT — 17_SETTINGS
A2: Decoupled Membrane Geometries, Constants & Kinetic Parameters | Author: Turgunjon Ruziboyev | Physics + AI Decision Support
A4: SETTINGS CONSTANT | B4: VALUE | C4: UNIT | D4: ENGINEERING BASIS
A5: Membrane Module Surface Area | B5: 50 | C5: m2 | D5: PVDF Hollow Fiber Module Specs
A6: Modules per Cassette | B6: 24 | C6: modules | D6: Cassette Frame Structural Geometry
A7: Cassettes per Train | B7: 4 | C7: cassettes | D7: Membrane Tank Layout
A8: Active Trains Count | B8: 4 | C8: trains | D8: Unit 77 Operational Train Count
A9: Standard Temperature Ref T_ref | B9: 20 | C9: °C | D9: Standard Water Industry Baseline
A10: Viscosity Temperature Factor theta | B10: 1.025 | C10: - | D10: Arrhenius / Empirical Viscosity Law
A11: Water Density rho | B11: 1000 | C11: kg/m3 | D11: Standard Liquid Water Density
A12: Clean Membrane Resistance Rm | B12: 520000000000 | C12: 1/m | D12: Virgin Factory Module Resistance
A13: Maximum Permissible TMP | B13: 60 | C13: kPa | D13: Manufacturer Fiber Collapse Threshold
A14: Design Operating Flux | B14: 24 | C14: LMH | D14: Nominal Sustained Production Flux
A15: Target Solids Retention Time (SRT) | B15: 20 | C15: days | D15: Biological Nitrification Target
A16: Biological Yield Y_obs | B16: 0.35 | C16: kg/kg | D16: Observed Biomass Synthesis Yield
A17: Biomass Decay Rate K_d | B17: 0.05 | C17: 1/d | D17: Endogenous Respiration Constant

Sheet 18_Engineering_Reference
A1: UNIT 77 MBR SUPER EXPERT — 18_ENGINEERING_REFERENCE
A2: Physical Equations, Symbol Nomenclature & Literature Citations | Author: Turgunjon Ruziboyev | Physics + AI Decision Support
A4: CONCEPT | B4: EQUATION / RELATION | C4: DIMENSIONS & UNITS | D4: LITERATURE CITATION
A5: Darcy Law Filtration | B5: J = TMP / (mu * R_tot) | C5: J in m/s, TMP in Pa, mu in Pa.s | D5: Darcy (1856); Judd (2011)
A6: Temperature Normalized Permeability | B6: Lp_20 = Lp * theta^(20 - T) | C6: Lp in LMH/bar, T in °C, theta=1.025 | D6: Water Environment Federation (2012)
A7: Water Viscosity Poiseuille | B7: mu(T) = 1.784 / (1 + 0.0337*T + 0.00022*T^2) | C7: mu in mPa.s, T in °C | D7: CRC Handbook of Chemistry & Physics
A8: Mean Cell Residence Time (SRT) | B8: SRT = (V_tank * MLSS) / (Q_was * MLSS_was) | C8: SRT in days, V in m3, Q in m3/d | D8: Metcalf & Eddy (5th Edition, 2014)
A9: Specific Aeration Demand (SADm) | B9: SAD_m = Q_air / Membrane_Area | C9: SAD_m in Nm3/(m2.h) | D9: EPA MBR Engineering Manual (2010)

Sheet 19_Audit_Log
A1: UNIT 77 MBR SUPER EXPERT — 19_AUDIT_LOG
A2: Version History, Verification Milestones & Engineering Sign-Offs | Author: Turgunjon Ruziboyev | Physics + AI Decision Support
A4: TIMESTAMP | B4: VERSION | C4: ACTION / EVENT | D4: ENGINEERING DETAILS | E4: VERIFIED BY
A5: 2026-09-18 13:48 | B5: v0.1.0 | C5: Stage 1 Sign-Off | D5: Engineering Foundation & Data Model 8/8 Gate Pass | E5: Turgunjon Ruziboyev
A6: 2026-09-18 13:52 | B6: v0.2.0 | C6: Stage 2 Workbook Build | D6: 19 Worksheets generated with structured formulas and no broken links | E6: Turgunjon Ruziboyev
A7: 2026-09-18 13:53 | B7: v0.2.0 | C7: Stage 2 Verification | D7: Formula reference audit, frozen headers check, and input separation check | E7: Automated Test Suite
A8: 2026-09-18 13:56 | B8: v0.3.0 | C8: Stage 3 Core Calcs | D8: Hydraulic, Poiseuille, Darcy & Biological SRT 12/12 Gate Pass (<0.01% err) | E8: Turgunjon Ruziboyev
A9: 2026-09-18 14:02 | B9: v0.4.0 | C9: Stage 4 Alarm Engine | D9: Hysteresis deadbands, persistence, ROC, Multi-Risk Index & peer Z-scores | E9: Turgunjon Ruziboyev
A10: 2026-09-18 14:08 | B10: v0.5.0 | C10: Stage 5 Dashboard & What-If | D10: Dynamic Outage Redistribution, Viscosity Compensation & WAS/SRT Sensitivity Engine | E10: Turgunjon Ruziboyev
A11: 2026-09-18 14:14 | B11: v0.6.0 | C11: Stage 6 Core Prediction & Tuning | D11: Multi-Horizon Forecasts, RUL Matrix, Darcy Rm Calibration & Automated Action Scheduling | E11: Turgunjon Ruziboyev
A12: 2026-09-18 14:20 | B12: v0.7.0 | C12: Stage 7 Python Foundation | D12: Modular pure-Python package with Darcy physics, biological mass balance & 100% parity | E12: Turgunjon Ruziboyev
A13: 2026-09-19 09:10 | B13: v0.8.0 | C13: Stage 8 Advanced Analytics | D13: Theil-Sen robust slopes, Hampel filter, PCA Hotelling T2, Isolation Forest & SHAP attributions | E13: Turgunjon Ruziboyev
A14: 2026-09-19 09:20 | B14: v0.9.0 | C14: Stage 9 Hybrid Bridge | D14: Two-Way Parity Verification (<0.05% diff), Heartbeat telemetry & Graceful Fallback State Machine | E14: Turgunjon Ruziboyev
A15: 2026-09-19 09:30 | B15: v1.0.0 | C15: Stage 10 Full Super Expert | D15: Multi-Domain Reasoning Chain, Physics Hypotheses, Prescriptive Operator Actions & Excel VBA Suite | E15: Turgunjon Ruziboyev
